hammurabi/__init__.py
hammurabi/config.py
hammurabi/exceptions.py
hammurabi/helpers.py
hammurabi/law.py
hammurabi/main.py
hammurabi/mixins.py
hammurabi/notifications/__init__.py
hammurabi/notifications/base.py
hammurabi/notifications/slack.py
hammurabi/pillar.py
hammurabi/preconditions/__init__.py
hammurabi/preconditions/attributes.py
hammurabi/preconditions/base.py
hammurabi/preconditions/directories.py
hammurabi/preconditions/files.py
hammurabi/preconditions/text.py
hammurabi/py.typed
hammurabi/reporters/__init__.py
hammurabi/reporters/base.py
hammurabi/reporters/json.py
hammurabi/rules/__init__.py
hammurabi/rules/abstract.py
hammurabi/rules/attributes.py
hammurabi/rules/base.py
hammurabi/rules/common.py
hammurabi/rules/dictionaries.py
hammurabi/rules/directories.py
hammurabi/rules/files.py
hammurabi/rules/ini.py
hammurabi/rules/json.py
hammurabi/rules/mixins.py
hammurabi/rules/operations.py
hammurabi/rules/templates.py
hammurabi/rules/text.py
hammurabi/rules/toml.py
hammurabi/rules/yaml.py
hammurabi-0.11.1.dist-info/entry_points.txt
hammurabi-0.11.1.dist-info/LICENSE
hammurabi-0.11.1.dist-info/WHEEL
hammurabi-0.11.1.dist-info/METADATA
hammurabi-0.11.1.dist-info/RECORD
