Metadata-Version: 2.1
Name: hammurabi
Version: 0.11.1
Summary: Hammurabi is an extensible CLI tool responsible for enforcing user-defined rules on a git repository.
Home-page: https://github.com/gabor-boros/hammurabi/
License: Apache-2.0
Keywords: automation,project,manipulate,rules,config,codemod
Author: Gábor Boros
Author-email: gabor.brs@gmail.com
Maintainer: Gábor Boros
Maintainer-email: gabor.brs@gmail.com
Requires-Python: >=3.7,<4.0
Classifier: Development Status :: 4 - Beta
Classifier: Environment :: Console
Classifier: Intended Audience :: Developers
Classifier: Intended Audience :: System Administrators
Classifier: License :: OSI Approved :: Apache Software License
Classifier: Natural Language :: English
Classifier: Operating System :: MacOS
Classifier: Operating System :: POSIX
Classifier: Operating System :: Unix
Classifier: Programming Language :: Python :: 3
Classifier: Programming Language :: Python :: 3 :: Only
Classifier: Programming Language :: Python :: 3.7
Classifier: Programming Language :: Python :: 3.8
Classifier: Programming Language :: Python :: 3.9
Classifier: Topic :: Software Development
Classifier: Topic :: Software Development :: Code Generators
Classifier: Topic :: Text Processing
Classifier: Topic :: Text Processing :: General
Provides-Extra: all
Provides-Extra: ini
Provides-Extra: slack-notifications
Provides-Extra: templating
Provides-Extra: ujson
Provides-Extra: yaml
Requires-Dist: configupdater (>=1.0.1,<2.0.0); extra == "all" or extra == "ini"
Requires-Dist: github3.py (>=1.3.0,<2.0.0)
Requires-Dist: gitpython (>=3.0.5,<4.0.0)
Requires-Dist: jinja2 (>=2.11.1,<3.0.0); extra == "all" or extra == "templating"
Requires-Dist: pydantic (>=1.4,<2.0)
Requires-Dist: ruamel.yaml (>=0.16.5,<0.17.0); extra == "all" or extra == "yaml"
Requires-Dist: slack-webhook (>=1.0.3,<2.0.0); extra == "all" or extra == "slack-notifications"
Requires-Dist: toml (>=0.10.1,<0.11.0)
Requires-Dist: typer (>=0.3.1,<0.4.0)
Requires-Dist: ujson (>=1.35,<5.0); extra == "all" or extra == "ujson"
Project-URL: Bug Tracker, https://github.com/gabor-boros/hammurabi/issues/
Project-URL: Documentation, https://readthedocs.org/projects/hammurabi/badge/
Project-URL: Repository, https://github.com/gabor-boros/hammurabi/
